Metadata-Version: 1.1
Name: typejudge
Version: 0.3.0
Summary: Automatically check for semver compliance based on type hints
Home-page: https://github.com/kragniz/typejudge
Author: Louis Taylor
Author-email: louis@kragniz.eu
License: UNKNOWN
Platform: UNKNOWN
Classifier: Development Status :: 2 - Pre-Alpha
Classifier: Programming Language :: Python
Classifier: Programming Language :: Python :: 3
Classifier: Programming Language :: Python :: 3.5
